{"LevelName":"Memories","TilesData":[[{"Position":{"X":0.0,"Y":4.772727},"Length":0.0,"Life":1,"Note":58,"Type":0},{"Position":{"X":0.0,"Y":11.25},"Length":0.0,"Life":1,"Note":75,"Type":0},{"Position":{"X":0.0,"Y":11.590909},"Length":0.0,"Life":1,"Note":78,"Type":0},{"Position":{"X":0.0,"Y":14.318182},"Length":0.0,"Life":1,"Note":75,"Type":0},{"Position":{"X":0.0,"Y":14.829545},"Length":0.0,"Life":1,"Note":73,"Type":0},{"Position":{"X":0.0,"Y":15.340908},"Length":0.0,"Life":1,"Note":71,"Type":0},{"Position":{"X":0.0,"Y":16.363636},"Length":0.0,"Life":1,"Note":68,"Type":0},{"Position":{"X":0.0,"Y":17.556818},"Length":0.0,"Life":1,"Note":66,"Type":0},{"Position":{"X":0.0,"Y":19.090908},"Length":0.0,"Life":1,"Note":66,"Type":0},{"Position":{"X":0.0,"Y":22.5},"Length":0.0,"Life":1,"Note":90,"Type":0},{"Position":{"X":0.0,"Y":24.886364},"Length":0.0,"Life":1,"Note":83,"Type":0},{"Position":{"X":0.0,"Y":25.568182},"Length":0.0,"Life":1,"Note":83,"Type":0},{"Position":{"X":0.0,"Y":26.25},"Length":0.0,"Life":1,"Note":83,"Type":0},{"Position":{"X":0.0,"Y":27.102272},"Length":0.0,"Life":1,"Note":83,"Type":0},{"Position":{"X":0.0,"Y":28.465908},"Length":0.0,"Life":1,"Note":78,"Type":0},{"Position":{"X":0.0,"Y":28.806816},"Length":0.0,"Life":1,"Note":78,"Type":0},{"Position":{"X":0.0,"Y":29.65909},"Length":0.0,"Life":1,"Note":78,"Type":0},{"Position":{"X":0.0,"Y":30.170454},"Length":0.0,"Life":1,"Note":80,"Type":0},{"Position":{"X":0.0,"Y":35.454544},"Length":0.0,"Life":1,"Note":75,"Type":0},{"Position":{"X":0.0,"Y":36.647728},"Length":0.0,"Life":1,"Note":75,"Type":0},{"Position":{"X":0.0,"Y":37.329544},"Length":0.0,"Life":1,"Note":76,"Type":0},{"Position":{"X":0.0,"Y":39.204544},"Length":0.0,"Life":1,"Note":73,"Type":0},{"Position":{"X":0.0,"Y":41.931816},"Length":0.0,"Life":1,"Note":71,"Type":0},{"Position":{"X":0.0,"Y":44.65909},"Length":0.0,"Life":1,"Note":83,"Type":0},{"Position":{"X":0.0,"Y":45.0},"Length":0.0,"Life":1,"Note":87,"Type":0},{"Position":{"X":0.0,"Y":45.85227},"Length":0.0,"Life":1,"Note":87,"Type":0},{"Position":{"X":0.0,"Y":47.386364},"Length":0.0,"Life":1,"Note":85,"Type":0},{"Position":{"X":0.0,"Y":47.897728},"Length":0.0,"Life":1,"Note":90,"Type":0},{"Position":{"X":0.0,"Y":48.579544},"Length":0.0,"Life":1,"Note":87,"Type":0},{"Position":{"X":0.0,"Y":50.113636},"Length":0.0,"Life":1,"Note":85,"Type":0},{"Position":{"X":0.0,"Y":51.306816},"Length":0.0,"Life":1,"Note":87,"Type":0},{"Position":{"X":0.0,"Y":52.15909},"Length":0.0,"Life":1,"Note":83,"Type":0},{"Position":{"X":0.0,"Y":54.204544},"Length":0.0,"Life":1,"Note":85,"Type":0},{"Position":{"X":0.0,"Y":56.761364},"Length":0.0,"Life":1,"Note":71,"Type":0},{"Position":{"X":0.0,"Y":57.954544},"Length":0.0,"Life":1,"Note":71,"Type":0},{"Position":{"X":0.0,"Y":59.147728},"Length":0.0,"Life":1,"Note":71,"Type":0},{"Position":{"X":0.0,"Y":60.0},"Length":0.0,"Life":1,"Note":70,"Type":0},{"Position":{"X":0.0,"Y":61.022728},"Length":0.0,"Life":1,"Note":71,"Type":0},{"Position":{"X":0.0,"Y":62.386364},"Length":0.0,"Life":1,"Note":71,"Type":0},{"Position":{"X":0.0,"Y":64.77273},"Length":0.0,"Life":1,"Note":78,"Type":0},{"Position":{"X":0.0,"Y":66.13636},"Length":0.0,"Life":1,"Note":95,"Type":0},{"Position":{"X":0.0,"Y":67.5},"Length":0.0,"Life":1,"Note":78,"Type":0},{"Position":{"X":0.0,"Y":69.88636},"Length":0.0,"Life":1,"Note":71,"Type":0},{"Position":{"X":0.0,"Y":70.56818},"Length":0.0,"Life":1,"Note":71,"Type":0},{"Position":{"X":0.0,"Y":71.25},"Length":0.0,"Life":1,"Note":71,"Type":0},{"Position":{"X":0.0,"Y":73.295456},"Length":0.0,"Life":1,"Note":68,"Type":0},{"Position":{"X":0.0,"Y":73.63636},"Length":0.0,"Life":1,"Note":68,"Type":0},{"Position":{"X":0.0,"Y":78.75},"Length":0.0,"Life":1,"Note":87,"Type":0},{"Position":{"X":0.0,"Y":82.15909},"Length":0.0,"Life":1,"Note":83,"Type":0},{"Position":{"X":0.0,"Y":82.840904},"Length":0.0,"Life":1,"Note":85,"Type":0},{"Position":{"X":0.0,"Y":83.181816},"Length":0.0,"Life":1,"Note":80,"Type":0},{"Position":{"X":0.0,"Y":83.86363},"Length":0.0,"Life":1,"Note":80,"Type":0},{"Position":{"X":0.0,"Y":84.375},"Length":0.0,"Life":1,"Note":78,"Type":0},{"Position":{"X":0.0,"Y":84.88636},"Length":0.0,"Life":1,"Note":78,"Type":0},{"Position":{"X":0.0,"Y":86.07954},"Length":0.0,"Life":1,"Note":80,"Type":0},{"Position":{"X":0.0,"Y":86.590904},"Length":0.0,"Life":1,"Note":80,"Type":0},{"Position":{"X":0.0,"Y":87.27273},"Length":0.0,"Life":1,"Note":82,"Type":0},{"Position":{"X":0.0,"Y":87.61363},"Length":0.0,"Life":1,"Note":82,"Type":0},{"Position":{"X":0.0,"Y":88.295456},"Length":0.0,"Life":1,"Note":83,"Type":0},{"Position":{"X":0.0,"Y":89.14773},"Length":0.0,"Life":1,"Note":78,"Type":0},{"Position":{"X":0.0,"Y":90.0},"Length":0.0,"Life":1,"Note":73,"Type":0},{"Position":{"X":0.0,"Y":91.875},"Length":0.0,"Life":1,"Note":76,"Type":0},{"Position":{"X":0.0,"Y":92.72727},"Length":0.0,"Life":1,"Note":73,"Type":0},{"Position":{"X":0.0,"Y":93.40909},"Length":0.0,"Life":1,"Note":73,"Type":0},{"Position":{"X":0.0,"Y":94.431816},"Length":0.0,"Life":1,"Note":75,"Type":0},{"Position":{"X":0.0,"Y":95.795456},"Length":0.0,"Life":1,"Note":73,"Type":0},{"Position":{"X":0.0,"Y":96.81818},"Length":0.0,"Life":1,"Note":71,"Type":0},{"Position":{"X":0.0,"Y":97.15909},"Length":0.0,"Life":1,"Note":71,"Type":0},{"Position":{"X":0.0,"Y":98.86363},"Length":0.0,"Life":1,"Note":70,"Type":0},{"Position":{"X":0.0,"Y":100.73863},"Length":0.0,"Life":1,"Note":73,"Type":0},{"Position":{"X":0.0,"Y":101.76136},"Length":0.0,"Life":1,"Note":75,"Type":0},{"Position":{"X":0.0,"Y":102.27273},"Length":0.0,"Life":1,"Note":75,"Type":0},{"Position":{"X":0.0,"Y":103.63636},"Length":0.0,"Life":1,"Note":76,"Type":0},{"Position":{"X":0.0,"Y":104.14773},"Length":0.0,"Life":1,"Note":76,"Type":0},{"Position":{"X":0.0,"Y":106.02273},"Length":0.0,"Life":1,"Note":73,"Type":0},{"Position":{"X":0.0,"Y":107.38636},"Length":0.0,"Life":1,"Note":75,"Type":0},{"Position":{"X":0.0,"Y":108.40909},"Length":0.0,"Life":1,"Note":71,"Type":0},{"Position":{"X":0.0,"Y":111.477264},"Length":0.0,"Life":1,"Note":83,"Type":0},{"Position":{"X":0.0,"Y":112.670456},"Length":0.0,"Life":1,"Note":87,"Type":0},{"Position":{"X":0.0,"Y":113.181816},"Length":0.0,"Life":1,"Note":87,"Type":0},{"Position":{"X":0.0,"Y":114.545456},"Length":0.0,"Life":1,"Note":88,"Type":0},{"Position":{"X":0.0,"Y":117.27273},"Length":0.0,"Life":1,"Note":88,"Type":0},{"Position":{"X":0.0,"Y":118.125},"Length":0.0,"Life":1,"Note":87,"Type":0},{"Position":{"X":0.0,"Y":119.65909},"Length":0.0,"Life":1,"Note":83,"Type":0},{"Position":{"X":0.0,"Y":120.0},"Length":0.0,"Life":1,"Note":83,"Type":0},{"Position":{"X":0.0,"Y":120.852264},"Length":0.0,"Life":1,"Note":88,"Type":0},{"Position":{"X":0.0,"Y":125.45454},"Length":0.0,"Life":1,"Note":71,"Type":0},{"Position":{"X":0.0,"Y":125.795456},"Length":0.0,"Life":1,"Note":71,"Type":0},{"Position":{"X":0.0,"Y":129.20454},"Length":0.0,"Life":1,"Note":71,"Type":0},{"Position":{"X":0.0,"Y":130.22726},"Length":0.0,"Life":1,"Note":71,"Type":0},{"Position":{"X":0.0,"Y":131.25},"Length":0.0,"Life":1,"Note":71,"Type":0},{"Position":{"X":0.0,"Y":131.59091},"Length":0.0,"Life":1,"Note":78,"Type":0},{"Position":{"X":0.0,"Y":132.27272},"Length":0.0,"Life":1,"Note":70,"Type":0},{"Position":{"X":0.0,"Y":132.95454},"Length":0.0,"Life":1,"Note":83,"Type":0},{"Position":{"X":0.0,"Y":133.97726},"Length":0.0,"Life":1,"Note":75,"Type":0},{"Position":{"X":0.0,"Y":134.31818},"Length":0.0,"Life":1,"Note":78,"Type":0},{"Position":{"X":0.0,"Y":135.17046},"Length":0.0,"Life":1,"Note":66,"Type":0},{"Position":{"X":0.0,"Y":136.36363},"Length":0.0,"Life":1,"Note":75,"Type":0},{"Position":{"X":0.0,"Y":137.04546},"Length":0.0,"Life":1,"Note":75,"Type":0},{"Position":{"X":0.0,"Y":137.55681},"Length":0.0,"Life":1,"Note":73,"Type":0},{"Position":{"X":0.0,"Y":138.40909},"Length":0.0,"Life":1,"Note":75,"Type":0},{"Position":{"X":0.0,"Y":138.92046},"Length":0.0,"Life":1,"Note":71,"Type":0},{"Position":{"X":0.0,"Y":139.77272},"Length":0.0,"Life":1,"Note":68,"Type":0},{"Position":{"X":0.0,"Y":140.625},"Length":0.0,"Life":1,"Note":66,"Type":0},{"Position":{"X":0.0,"Y":141.81818},"Length":0.0,"Life":1,"Note":68,"Type":0},{"Position":{"X":0.0,"Y":143.35226},"Length":0.0,"Life":1,"Note":71,"Type":0},{"Position":{"X":0.0,"Y":144.09091},"Length":0.0,"Life":1,"Note":82,"Type":0},{"Position":{"X":0.0,"Y":144.31818},"Length":0.0,"Life":1,"Note":85,"Type":0},{"Position":{"X":0.0,"Y":144.88635},"Length":0.0,"Life":1,"Note":87,"Type":0},{"Position":{"X":0.0,"Y":145.73863},"Length":0.0,"Life":1,"Note":88,"Type":0},{"Position":{"X":0.0,"Y":146.07954},"Length":0.0,"Life":1,"Note":78,"Type":0},{"Position":{"X":0.0,"Y":146.93181},"Length":0.0,"Life":1,"Note":87,"Type":0},{"Position":{"X":0.0,"Y":148.46591},"Length":0.0,"Life":1,"Note":76,"Type":0},{"Position":{"X":0.0,"Y":148.80681},"Length":0.0,"Life":1,"Note":80,"Type":0},{"Position":{"X":0.0,"Y":149.48863},"Length":0.0,"Life":1,"Note":83,"Type":0},{"Position":{"X":0.0,"Y":149.82954},"Length":0.0,"Life":1,"Note":83,"Type":0},{"Position":{"X":0.0,"Y":152.04546},"Length":0.0,"Life":1,"Note":78,"Type":0},{"Position":{"X":0.0,"Y":152.55681},"Length":0.0,"Life":1,"Note":82,"Type":0},{"Position":{"X":0.0,"Y":153.75},"Length":0.0,"Life":1,"Note":83,"Type":0},{"Position":{"X":0.0,"Y":154.26135},"Length":0.0,"Life":1,"Note":82,"Type":0},{"Position":{"X":0.0,"Y":155.96591},"Length":0.0,"Life":1,"Note":78,"Type":0},{"Position":{"X":0.0,"Y":157.15909},"Length":0.0,"Life":1,"Note":73,"Type":0},{"Position":{"X":0.0,"Y":159.03409},"Length":0.0,"Life":1,"Note":75,"Type":0},{"Position":{"X":0.0,"Y":160.22726},"Length":0.0,"Life":1,"Note":73,"Type":0},{"Position":{"X":0.0,"Y":161.07954},"Length":0.0,"Life":1,"Note":73,"Type":0},{"Position":{"X":0.0,"Y":161.42046},"Length":0.0,"Life":1,"Note":76,"Type":0},{"Position":{"X":0.0,"Y":162.95454},"Length":0.0,"Life":1,"Note":73,"Type":0},{"Position":{"X":0.0,"Y":163.80681},"Length":0.0,"Life":1,"Note":71,"Type":0},{"Position":{"X":0.0,"Y":165.17046},"Length":0.0,"Life":1,"Note":70,"Type":0},{"Position":{"X":0.0,"Y":168.40907},"Length":0.0,"Life":1,"Note":70,"Type":0},{"Position":{"X":0.0,"Y":172.15907},"Length":0.0,"Life":1,"Note":59,"Type":0},{"Position":{"X":0.0,"Y":174.88635},"Length":0.0,"Life":1,"Note":59,"Type":0},{"Position":{"X":0.0,"Y":177.27272},"Length":0.0,"Life":1,"Note":71,"Type":0}],[{"Position":{"X":1.0,"Y":0.6818182},"Length":0.0,"Life":1,"Note":63,"Type":0},{"Position":{"X":1.0,"Y":7.5},"Length":0.0,"Life":1,"Note":63,"Type":0},{"Position":{"X":1.0,"Y":11.931817},"Length":0.0,"Life":1,"Note":75,"Type":0},{"Position":{"X":1.0,"Y":13.636363},"Length":0.0,"Life":1,"Note":75,"Type":0},{"Position":{"X":1.0,"Y":14.147727},"Length":0.0,"Life":1,"Note":73,"Type":0},{"Position":{"X":1.0,"Y":15.511363},"Length":0.0,"Life":1,"Note":73,"Type":0},{"Position":{"X":1.0,"Y":16.022726},"Length":0.0,"Life":1,"Note":73,"Type":0},{"Position":{"X":1.0,"Y":16.704544},"Length":0.0,"Life":1,"Note":68,"Type":0},{"Position":{"X":1.0,"Y":18.068182},"Length":0.0,"Life":1,"Note":66,"Type":0},{"Position":{"X":1.0,"Y":19.431818},"Length":0.0,"Life":1,"Note":68,"Type":0},{"Position":{"X":1.0,"Y":20.113636},"Length":0.0,"Life":1,"Note":71,"Type":0},{"Position":{"X":1.0,"Y":21.818182},"Length":0.0,"Life":1,"Note":90,"Type":0},{"Position":{"X":1.0,"Y":22.329544},"Length":0.0,"Life":1,"Note":88,"Type":0},{"Position":{"X":1.0,"Y":23.011364},"Length":0.0,"Life":1,"Note":88,"Type":0},{"Position":{"X":1.0,"Y":25.056818},"Length":0.0,"Life":1,"Note":85,"Type":0},{"Position":{"X":1.0,"Y":25.90909},"Length":0.0,"Life":1,"Note":87,"Type":0},{"Position":{"X":1.0,"Y":26.590908},"Length":0.0,"Life":1,"Note":87,"Type":0},{"Position":{"X":1.0,"Y":27.272726},"Length":0.0,"Life":1,"Note":80,"Type":0},{"Position":{"X":1.0,"Y":27.954544},"Length":0.0,"Life":1,"Note":80,"Type":0},{"Position":{"X":1.0,"Y":28.636364},"Length":0.0,"Life":1,"Note":80,"Type":0},{"Position":{"X":1.0,"Y":30.681816},"Length":0.0,"Life":1,"Note":80,"Type":0},{"Position":{"X":1.0,"Y":31.363634},"Length":0.0,"Life":1,"Note":82,"Type":0},{"Position":{"X":1.0,"Y":32.045452},"Length":0.0,"Life":1,"Note":82,"Type":0},{"Position":{"X":1.0,"Y":32.727272},"Length":0.0,"Life":1,"Note":83,"Type":0},{"Position":{"X":1.0,"Y":33.920452},"Length":0.0,"Life":1,"Note":73,"Type":0},{"Position":{"X":1.0,"Y":34.431816},"Length":0.0,"Life":1,"Note":78,"Type":0},{"Position":{"X":1.0,"Y":34.94318},"Length":0.0,"Life":1,"Note":75,"Type":0},{"Position":{"X":1.0,"Y":37.840908},"Length":0.0,"Life":1,"Note":71,"Type":0},{"Position":{"X":1.0,"Y":40.56818},"Length":0.0,"Life":1,"Note":75,"Type":0},{"Position":{"X":1.0,"Y":41.590908},"Length":0.0,"Life":1,"Note":71,"Type":0},{"Position":{"X":1.0,"Y":42.10227},"Length":0.0,"Life":1,"Note":71,"Type":0},{"Position":{"X":1.0,"Y":42.613636},"Length":0.0,"Life":1,"Note":71,"Type":0},{"Position":{"X":1.0,"Y":43.295452},"Length":0.0,"Life":1,"Note":73,"Type":0},{"Position":{"X":1.0,"Y":44.829544},"Length":0.0,"Life":1,"Note":85,"Type":0},{"Position":{"X":1.0,"Y":46.022728},"Length":0.0,"Life":1,"Note":92,"Type":0},{"Position":{"X":1.0,"Y":47.556816},"Length":0.0,"Life":1,"Note":87,"Type":0},{"Position":{"X":1.0,"Y":50.28409},"Length":0.0,"Life":1,"Note":87,"Type":0},{"Position":{"X":1.0,"Y":50.965908},"Length":0.0,"Life":1,"Note":88,"Type":0},{"Position":{"X":1.0,"Y":52.840908},"Length":0.0,"Life":1,"Note":83,"Type":0},{"Position":{"X":1.0,"Y":53.181816},"Length":0.0,"Life":1,"Note":83,"Type":0},{"Position":{"X":1.0,"Y":54.03409},"Length":0.0,"Life":1,"Note":88,"Type":0},{"Position":{"X":1.0,"Y":56.931816},"Length":0.0,"Life":1,"Note":71,"Type":0},{"Position":{"X":1.0,"Y":57.272728},"Length":0.0,"Life":1,"Note":75,"Type":0},{"Position":{"X":1.0,"Y":58.636364},"Length":0.0,"Life":1,"Note":71,"Type":0},{"Position":{"X":1.0,"Y":58.97727},"Length":0.0,"Life":1,"Note":71,"Type":0},{"Position":{"X":1.0,"Y":59.31818},"Length":0.0,"Life":1,"Note":75,"Type":0},{"Position":{"X":1.0,"Y":60.681816},"Length":0.0,"Life":1,"Note":70,"Type":0},{"Position":{"X":1.0,"Y":62.72727},"Length":0.0,"Life":1,"Note":75,"Type":0},{"Position":{"X":1.0,"Y":64.431816},"Length":0.0,"Life":1,"Note":71,"Type":0},{"Position":{"X":1.0,"Y":66.13636},"Length":0.0,"Life":1,"Note":83,"Type":0},{"Position":{"X":1.0,"Y":67.15909},"Length":0.0,"Life":1,"Note":75,"Type":0},{"Position":{"X":1.0,"Y":67.840904},"Length":0.0,"Life":1,"Note":75,"Type":0},{"Position":{"X":1.0,"Y":69.545456},"Length":0.0,"Life":1,"Note":75,"Type":0},{"Position":{"X":1.0,"Y":70.22727},"Length":0.0,"Life":1,"Note":75,"Type":0},{"Position":{"X":1.0,"Y":70.73863},"Length":0.0,"Life":1,"Note":73,"Type":0},{"Position":{"X":1.0,"Y":71.590904},"Length":0.0,"Life":1,"Note":75,"Type":0},{"Position":{"X":1.0,"Y":72.27273},"Length":0.0,"Life":1,"Note":68,"Type":0},{"Position":{"X":1.0,"Y":73.465904},"Length":0.0,"Life":1,"Note":66,"Type":0},{"Position":{"X":1.0,"Y":73.97727},"Length":0.0,"Life":1,"Note":66,"Type":0},{"Position":{"X":1.0,"Y":75.681816},"Length":0.0,"Life":1,"Note":68,"Type":0},{"Position":{"X":1.0,"Y":76.36363},"Length":0.0,"Life":1,"Note":70,"Type":0},{"Position":{"X":1.0,"Y":78.06818},"Length":0.0,"Life":1,"Note":87,"Type":0},{"Position":{"X":1.0,"Y":81.47727},"Length":0.0,"Life":1,"Note":83,"Type":0},{"Position":{"X":1.0,"Y":81.81818},"Length":0.0,"Life":1,"Note":87,"Type":0},{"Position":{"X":1.0,"Y":83.52273},"Length":0.0,"Life":1,"Note":80,"Type":0},{"Position":{"X":1.0,"Y":84.715904},"Length":0.0,"Life":1,"Note":78,"Type":0},{"Position":{"X":1.0,"Y":85.90909},"Length":0.0,"Life":1,"Note":80,"Type":0},{"Position":{"X":1.0,"Y":89.48863},"Length":0.0,"Life":1,"Note":75,"Type":0},{"Position":{"X":1.0,"Y":90.681816},"Length":0.0,"Life":1,"Note":73,"Type":0},{"Position":{"X":1.0,"Y":91.53409},"Length":0.0,"Life":1,"Note":73,"Type":0},{"Position":{"X":1.0,"Y":94.26136},"Length":0.0,"Life":1,"Note":73,"Type":0},{"Position":{"X":1.0,"Y":95.45454},"Length":0.0,"Life":1,"Note":73,"Type":0},{"Position":{"X":1.0,"Y":96.13636},"Length":0.0,"Life":1,"Note":73,"Type":0},{"Position":{"X":1.0,"Y":98.35227},"Length":0.0,"Life":1,"Note":70,"Type":0},{"Position":{"X":1.0,"Y":100.56818},"Length":0.0,"Life":1,"Note":71,"Type":0},{"Position":{"X":1.0,"Y":101.25},"Length":0.0,"Life":1,"Note":78,"Type":0},{"Position":{"X":1.0,"Y":101.931816},"Length":0.0,"Life":1,"Note":80,"Type":0},{"Position":{"X":1.0,"Y":103.295456},"Length":0.0,"Life":1,"Note":73,"Type":0},{"Position":{"X":1.0,"Y":103.97727},"Length":0.0,"Life":1,"Note":76,"Type":0},{"Position":{"X":1.0,"Y":104.48863},"Length":0.0,"Life":1,"Note":75,"Type":0},{"Position":{"X":1.0,"Y":106.53409},"Length":0.0,"Life":1,"Note":76,"Type":0},{"Position":{"X":1.0,"Y":108.920456},"Length":0.0,"Life":1,"Note":71,"Type":0},{"Position":{"X":1.0,"Y":109.602264},"Length":0.0,"Life":1,"Note":75,"Type":0},{"Position":{"X":1.0,"Y":111.64773},"Length":0.0,"Life":1,"Note":85,"Type":0},{"Position":{"X":1.0,"Y":112.15909},"Length":0.0,"Life":1,"Note":90,"Type":0},{"Position":{"X":1.0,"Y":114.375},"Length":0.0,"Life":1,"Note":87,"Type":0},{"Position":{"X":1.0,"Y":114.715904},"Length":0.0,"Life":1,"Note":90,"Type":0},{"Position":{"X":1.0,"Y":115.39773},"Length":0.0,"Life":1,"Note":87,"Type":0},{"Position":{"X":1.0,"Y":117.102264},"Length":0.0,"Life":1,"Note":87,"Type":0},{"Position":{"X":1.0,"Y":117.78409},"Length":0.0,"Life":1,"Note":88,"Type":0},{"Position":{"X":1.0,"Y":118.295456},"Length":0.0,"Life":1,"Note":87,"Type":0},{"Position":{"X":1.0,"Y":119.82954},"Length":0.0,"Life":1,"Note":83,"Type":0},{"Position":{"X":1.0,"Y":123.40909},"Length":0.0,"Life":1,"Note":71,"Type":0},{"Position":{"X":1.0,"Y":124.090904},"Length":0.0,"Life":1,"Note":75,"Type":0},{"Position":{"X":1.0,"Y":124.77273},"Length":0.0,"Life":1,"Note":71,"Type":0},{"Position":{"X":1.0,"Y":125.625},"Length":0.0,"Life":1,"Note":71,"Type":0},{"Position":{"X":1.0,"Y":126.81818},"Length":0.0,"Life":1,"Note":70,"Type":0},{"Position":{"X":1.0,"Y":128.86363},"Length":0.0,"Life":1,"Note":71,"Type":0},{"Position":{"X":1.0,"Y":129.54546},"Length":0.0,"Life":1,"Note":75,"Type":0},{"Position":{"X":1.0,"Y":130.90909},"Length":0.0,"Life":1,"Note":71,"Type":0},{"Position":{"X":1.0,"Y":134.14772},"Length":0.0,"Life":1,"Note":76,"Type":0},{"Position":{"X":1.0,"Y":134.82954},"Length":0.0,"Life":1,"Note":76,"Type":0},{"Position":{"X":1.0,"Y":135.51135},"Length":0.0,"Life":1,"Note":70,"Type":0},{"Position":{"X":1.0,"Y":135.85226},"Length":0.0,"Life":1,"Note":73,"Type":0},{"Position":{"X":1.0,"Y":136.19318},"Length":0.0,"Life":1,"Note":76,"Type":0},{"Position":{"X":1.0,"Y":136.70454},"Length":0.0,"Life":1,"Note":71,"Type":0},{"Position":{"X":1.0,"Y":137.38635},"Length":0.0,"Life":1,"Note":71,"Type":0},{"Position":{"X":1.0,"Y":137.72726},"Length":0.0,"Life":1,"Note":75,"Type":0},{"Position":{"X":1.0,"Y":138.23863},"Length":0.0,"Life":1,"Note":73,"Type":0},{"Position":{"X":1.0,"Y":139.09091},"Length":0.0,"Life":1,"Note":68,"Type":0},{"Position":{"X":1.0,"Y":140.28409},"Length":0.0,"Life":1,"Note":66,"Type":0},{"Position":{"X":1.0,"Y":140.79546},"Length":0.0,"Life":1,"Note":66,"Type":0},{"Position":{"X":1.0,"Y":141.98863},"Length":0.0,"Life":1,"Note":68,"Type":0},{"Position":{"X":1.0,"Y":142.5},"Length":0.0,"Life":1,"Note":68,"Type":0},{"Position":{"X":1.0,"Y":143.97726},"Length":0.0,"Life":1,"Note":80,"Type":0},{"Position":{"X":1.0,"Y":144.43181},"Length":0.0,"Life":1,"Note":87,"Type":0},{"Position":{"X":1.0,"Y":146.25},"Length":0.0,"Life":1,"Note":80,"Type":0},{"Position":{"X":1.0,"Y":146.59091},"Length":0.0,"Life":1,"Note":83,"Type":0},{"Position":{"X":1.0,"Y":147.78409},"Length":0.0,"Life":1,"Note":85,"Type":0},{"Position":{"X":1.0,"Y":148.29546},"Length":0.0,"Life":1,"Note":75,"Type":0},{"Position":{"X":1.0,"Y":148.97726},"Length":0.0,"Life":1,"Note":78,"Type":0},{"Position":{"X":1.0,"Y":149.31818},"Length":0.0,"Life":1,"Note":78,"Type":0},{"Position":{"X":1.0,"Y":149.65909},"Length":0.0,"Life":1,"Note":82,"Type":0},{"Position":{"X":1.0,"Y":150.0},"Length":0.0,"Life":1,"Note":80,"Type":0},{"Position":{"X":1.0,"Y":151.19318},"Length":0.0,"Life":1,"Note":76,"Type":0},{"Position":{"X":1.0,"Y":151.53409},"Length":0.0,"Life":1,"Note":76,"Type":0},{"Position":{"X":1.0,"Y":151.875},"Length":0.0,"Life":1,"Note":76,"Type":0},{"Position":{"X":1.0,"Y":152.89772},"Length":0.0,"Life":1,"Note":80,"Type":0},{"Position":{"X":1.0,"Y":153.40909},"Length":0.0,"Life":1,"Note":80,"Type":0},{"Position":{"X":1.0,"Y":154.77272},"Length":0.0,"Life":1,"Note":82,"Type":0},{"Position":{"X":1.0,"Y":156.30681},"Length":0.0,"Life":1,"Note":75,"Type":0},{"Position":{"X":1.0,"Y":157.5},"Length":0.0,"Life":1,"Note":73,"Type":0},{"Position":{"X":1.0,"Y":158.35226},"Length":0.0,"Life":1,"Note":73,"Type":0},{"Position":{"X":1.0,"Y":159.54546},"Length":0.0,"Life":1,"Note":73,"Type":0},{"Position":{"X":1.0,"Y":162.61363},"Length":0.0,"Life":1,"Note":73,"Type":0},{"Position":{"X":1.0,"Y":163.63635},"Length":0.0,"Life":1,"Note":71,"Type":0},{"Position":{"X":1.0,"Y":165.0},"Length":0.0,"Life":1,"Note":70,"Type":0},{"Position":{"X":1.0,"Y":166.02272},"Length":0.0,"Life":1,"Note":71,"Type":0},{"Position":{"X":1.0,"Y":166.70454},"Length":0.0,"Life":1,"Note":66,"Type":0},{"Position":{"X":1.0,"Y":169.43181},"Length":0.0,"Life":1,"Note":63,"Type":0},{"Position":{"X":1.0,"Y":173.86363},"Length":0.0,"Life":1,"Note":71,"Type":0},{"Position":{"X":1.0,"Y":175.22726},"Length":0.0,"Life":1,"Note":64,"Type":0}],[{"Position":{"X":2.0,"Y":3.4090908},"Length":0.0,"Life":1,"Note":59,"Type":0},{"Position":{"X":2.0,"Y":10.227272},"Length":0.0,"Life":1,"Note":58,"Type":0},{"Position":{"X":2.0,"Y":12.102272},"Length":0.0,"Life":1,"Note":76,"Type":0},{"Position":{"X":2.0,"Y":14.659091},"Length":0.0,"Life":1,"Note":71,"Type":0},{"Position":{"X":2.0,"Y":15.0},"Length":0.0,"Life":1,"Note":75,"Type":0},{"Position":{"X":2.0,"Y":15.681817},"Length":0.0,"Life":1,"Note":75,"Type":0},{"Position":{"X":2.0,"Y":16.193182},"Length":0.0,"Life":1,"Note":71,"Type":0},{"Position":{"X":2.0,"Y":17.386364},"Length":0.0,"Life":1,"Note":68,"Type":0},{"Position":{"X":2.0,"Y":17.897726},"Length":0.0,"Life":1,"Note":66,"Type":0},{"Position":{"X":2.0,"Y":19.154829},"Length":0.0,"Life":1,"Note":68,"Type":0},{"Position":{"X":2.0,"Y":19.772726},"Length":0.0,"Life":1,"Note":68,"Type":0},{"Position":{"X":2.0,"Y":22.15909},"Length":0.0,"Life":1,"Note":87,"Type":0},{"Position":{"X":2.0,"Y":22.840908},"Length":0.0,"Life":1,"Note":87,"Type":0},{"Position":{"X":2.0,"Y":23.181818},"Length":0.0,"Life":1,"Note":90,"Type":0},{"Position":{"X":2.0,"Y":25.227272},"Length":0.0,"Life":1,"Note":87,"Type":0},{"Position":{"X":2.0,"Y":25.738634},"Length":0.0,"Life":1,"Note":85,"Type":0},{"Position":{"X":2.0,"Y":26.931816},"Length":0.0,"Life":1,"Note":85,"Type":0},{"Position":{"X":2.0,"Y":27.613634},"Length":0.0,"Life":1,"Note":80,"Type":0},{"Position":{"X":2.0,"Y":28.977272},"Length":0.0,"Life":1,"Note":78,"Type":0},{"Position":{"X":2.0,"Y":30.0},"Length":0.0,"Life":1,"Note":80,"Type":0},{"Position":{"X":2.0,"Y":30.340908},"Length":0.0,"Life":1,"Note":80,"Type":0},{"Position":{"X":2.0,"Y":31.53409},"Length":0.0,"Life":1,"Note":82,"Type":0},{"Position":{"X":2.0,"Y":32.386364},"Length":0.0,"Life":1,"Note":83,"Type":0},{"Position":{"X":2.0,"Y":34.090908},"Length":0.0,"Life":1,"Note":75,"Type":0},{"Position":{"X":2.0,"Y":34.602272},"Length":0.0,"Life":1,"Note":78,"Type":0},{"Position":{"X":2.0,"Y":36.81818},"Length":0.0,"Life":1,"Note":76,"Type":0},{"Position":{"X":2.0,"Y":39.375},"Length":0.0,"Life":1,"Note":75,"Type":0},{"Position":{"X":2.0,"Y":39.715908},"Length":0.0,"Life":1,"Note":76,"Type":0},{"Position":{"X":2.0,"Y":41.25},"Length":0.0,"Life":1,"Note":73,"Type":0},{"Position":{"X":2.0,"Y":42.272728},"Length":0.0,"Life":1,"Note":71,"Type":0},{"Position":{"X":2.0,"Y":43.125},"Length":0.0,"Life":1,"Note":76,"Type":0},{"Position":{"X":2.0,"Y":45.340908},"Length":0.0,"Life":1,"Note":90,"Type":0},{"Position":{"X":2.0,"Y":46.363636},"Length":0.0,"Life":1,"Note":87,"Type":0},{"Position":{"X":2.0,"Y":47.72727},"Length":0.0,"Life":1,"Note":88,"Type":0},{"Position":{"X":2.0,"Y":50.625},"Length":0.0,"Life":1,"Note":88,"Type":0},{"Position":{"X":2.0,"Y":51.47727},"Length":0.0,"Life":1,"Note":87,"Type":0},{"Position":{"X":2.0,"Y":53.69318},"Length":0.0,"Life":1,"Note":87,"Type":0},{"Position":{"X":2.0,"Y":55.22727},"Length":0.0,"Life":1,"Note":95,"Type":0},{"Position":{"X":2.0,"Y":59.65909},"Length":0.0,"Life":1,"Note":71,"Type":0},{"Position":{"X":2.0,"Y":62.215908},"Length":0.0,"Life":1,"Note":71,"Type":0},{"Position":{"X":2.0,"Y":63.40909},"Length":0.0,"Life":1,"Note":71,"Type":0},{"Position":{"X":2.0,"Y":65.11363},"Length":0.0,"Life":1,"Note":71,"Type":0},{"Position":{"X":2.0,"Y":66.81818},"Length":0.0,"Life":1,"Note":78,"Type":0},{"Position":{"X":2.0,"Y":68.181816},"Length":0.0,"Life":1,"Note":78,"Type":0},{"Position":{"X":2.0,"Y":70.056816},"Length":0.0,"Life":1,"Note":73,"Type":0},{"Position":{"X":2.0,"Y":72.10227},"Length":0.0,"Life":1,"Note":71,"Type":0},{"Position":{"X":2.0,"Y":72.61363},"Length":0.0,"Life":1,"Note":68,"Type":0},{"Position":{"X":2.0,"Y":73.806816},"Length":0.0,"Life":1,"Note":66,"Type":0},{"Position":{"X":2.0,"Y":74.65909},"Length":0.0,"Life":1,"Note":66,"Type":0},{"Position":{"X":2.0,"Y":75.170456},"Length":0.0,"Life":1,"Note":68,"Type":0},{"Position":{"X":2.0,"Y":76.02273},"Length":0.0,"Life":1,"Note":71,"Type":0},{"Position":{"X":2.0,"Y":77.72727},"Length":0.0,"Life":1,"Note":90,"Type":0},{"Position":{"X":2.0,"Y":78.23863},"Length":0.0,"Life":1,"Note":88,"Type":0},{"Position":{"X":2.0,"Y":79.090904},"Length":0.0,"Life":1,"Note":90,"Type":0},{"Position":{"X":2.0,"Y":80.795456},"Length":0.0,"Life":1,"Note":83,"Type":0},{"Position":{"X":2.0,"Y":81.13636},"Length":0.0,"Life":1,"Note":87,"Type":0},{"Position":{"X":2.0,"Y":81.64773},"Length":0.0,"Life":1,"Note":85,"Type":0},{"Position":{"X":2.0,"Y":82.32954},"Length":0.0,"Life":1,"Note":85,"Type":0},{"Position":{"X":2.0,"Y":83.01136},"Length":0.0,"Life":1,"Note":83,"Type":0},{"Position":{"X":2.0,"Y":84.20454},"Length":0.0,"Life":1,"Note":80,"Type":0},{"Position":{"X":2.0,"Y":86.931816},"Length":0.0,"Life":1,"Note":83,"Type":0},{"Position":{"X":2.0,"Y":90.340904},"Length":0.0,"Life":1,"Note":73,"Type":0},{"Position":{"X":2.0,"Y":91.19318},"Length":0.0,"Life":1,"Note":71,"Type":0},{"Position":{"X":2.0,"Y":92.215904},"Length":0.0,"Life":1,"Note":75,"Type":0},{"Position":{"X":2.0,"Y":94.60227},"Length":0.0,"Life":1,"Note":76,"Type":0},{"Position":{"X":2.0,"Y":97.840904},"Length":0.0,"Life":1,"Note":71,"Type":0},{"Position":{"X":2.0,"Y":98.52273},"Length":0.0,"Life":1,"Note":70,"Type":0},{"Position":{"X":2.0,"Y":100.90909},"Length":0.0,"Life":1,"Note":75,"Type":0},{"Position":{"X":2.0,"Y":101.420456},"Length":0.0,"Life":1,"Note":78,"Type":0},{"Position":{"X":2.0,"Y":103.465904},"Length":0.0,"Life":1,"Note":75,"Type":0},{"Position":{"X":2.0,"Y":104.65909},"Length":0.0,"Life":1,"Note":71,"Type":0},{"Position":{"X":2.0,"Y":106.19318},"Length":0.0,"Life":1,"Note":75,"Type":0},{"Position":{"X":2.0,"Y":106.875},"Length":0.0,"Life":1,"Note":76,"Type":0},{"Position":{"X":2.0,"Y":109.090904},"Length":0.0,"Life":1,"Note":71,"Type":0},{"Position":{"X":2.0,"Y":109.94318},"Length":0.0,"Life":1,"Note":76,"Type":0},{"Position":{"X":2.0,"Y":112.840904},"Length":0.0,"Life":1,"Note":92,"Type":0},{"Position":{"X":2.0,"Y":115.056816},"Length":0.0,"Life":1,"Note":88,"Type":0},{"Position":{"X":2.0,"Y":116.931816},"Length":0.0,"Life":1,"Note":85,"Type":0},{"Position":{"X":2.0,"Y":118.977264},"Length":0.0,"Life":1,"Note":83,"Type":0},{"Position":{"X":2.0,"Y":120.51136},"Length":0.0,"Life":1,"Note":87,"Type":0},{"Position":{"X":2.0,"Y":122.045456},"Length":0.0,"Life":1,"Note":95,"Type":0},{"Position":{"X":2.0,"Y":123.75},"Length":0.0,"Life":1,"Note":71,"Type":0},{"Position":{"X":2.0,"Y":125.965904},"Length":0.0,"Life":1,"Note":71,"Type":0},{"Position":{"X":2.0,"Y":126.477264},"Length":0.0,"Life":1,"Note":71,"Type":0},{"Position":{"X":2.0,"Y":127.840904},"Length":0.0,"Life":1,"Note":71,"Type":0},{"Position":{"X":2.0,"Y":129.37498},"Length":0.0,"Life":1,"Note":71,"Type":0},{"Position":{"X":2.0,"Y":129.88635},"Length":0.0,"Life":1,"Note":71,"Type":0},{"Position":{"X":2.0,"Y":131.42046},"Length":0.0,"Life":1,"Note":71,"Type":0},{"Position":{"X":2.0,"Y":133.63635},"Length":0.0,"Life":1,"Note":78,"Type":0},{"Position":{"X":2.0,"Y":135.34091},"Length":0.0,"Life":1,"Note":68,"Type":0},{"Position":{"X":2.0,"Y":135.68181},"Length":0.0,"Life":1,"Note":71,"Type":0},{"Position":{"X":2.0,"Y":136.02272},"Length":0.0,"Life":1,"Note":75,"Type":0},{"Position":{"X":2.0,"Y":136.875},"Length":0.0,"Life":1,"Note":73,"Type":0},{"Position":{"X":2.0,"Y":138.06818},"Length":0.0,"Life":1,"Note":71,"Type":0},{"Position":{"X":2.0,"Y":138.75},"Length":0.0,"Life":1,"Note":73,"Type":0},{"Position":{"X":2.0,"Y":140.11363},"Length":0.0,"Life":1,"Note":68,"Type":0},{"Position":{"X":2.0,"Y":140.45454},"Length":0.0,"Life":1,"Note":68,"Type":0},{"Position":{"X":2.0,"Y":141.47726},"Length":0.0,"Life":1,"Note":66,"Type":0},{"Position":{"X":2.0,"Y":142.15909},"Length":0.0,"Life":1,"Note":68,"Type":0},{"Position":{"X":2.0,"Y":142.84091},"Length":0.0,"Life":1,"Note":71,"Type":0},{"Position":{"X":2.0,"Y":143.69318},"Length":0.0,"Life":1,"Note":75,"Type":0},{"Position":{"X":2.0,"Y":144.20454},"Length":0.0,"Life":1,"Note":83,"Type":0},{"Position":{"X":2.0,"Y":144.54546},"Length":0.0,"Life":1,"Note":90,"Type":0},{"Position":{"X":2.0,"Y":145.05681},"Length":0.0,"Life":1,"Note":88,"Type":0},{"Position":{"X":2.0,"Y":145.56818},"Length":0.0,"Life":1,"Note":87,"Type":0},{"Position":{"X":2.0,"Y":145.90909},"Length":0.0,"Life":1,"Note":90,"Type":0},{"Position":{"X":2.0,"Y":147.27272},"Length":0.0,"Life":1,"Note":87,"Type":0},{"Position":{"X":2.0,"Y":147.95454},"Length":0.0,"Life":1,"Note":87,"Type":0},{"Position":{"X":2.0,"Y":148.63635},"Length":0.0,"Life":1,"Note":78,"Type":0},{"Position":{"X":2.0,"Y":150.34091},"Length":0.0,"Life":1,"Note":83,"Type":0},{"Position":{"X":2.0,"Y":150.68181},"Length":0.0,"Life":1,"Note":80,"Type":0},{"Position":{"X":2.0,"Y":151.70454},"Length":0.0,"Life":1,"Note":75,"Type":0},{"Position":{"X":2.0,"Y":152.38635},"Length":0.0,"Life":1,"Note":83,"Type":0},{"Position":{"X":2.0,"Y":154.43181},"Length":0.0,"Life":1,"Note":82,"Type":0},{"Position":{"X":2.0,"Y":155.11363},"Length":0.0,"Life":1,"Note":83,"Type":0},{"Position":{"X":2.0,"Y":156.81818},"Length":0.0,"Life":1,"Note":73,"Type":0},{"Position":{"X":2.0,"Y":158.01135},"Length":0.0,"Life":1,"Note":71,"Type":0},{"Position":{"X":2.0,"Y":158.69318},"Length":0.0,"Life":1,"Note":76,"Type":0},{"Position":{"X":2.0,"Y":159.88635},"Length":0.0,"Life":1,"Note":73,"Type":0},{"Position":{"X":2.0,"Y":160.73863},"Length":0.0,"Life":1,"Note":71,"Type":0},{"Position":{"X":2.0,"Y":161.25},"Length":0.0,"Life":1,"Note":75,"Type":0},{"Position":{"X":2.0,"Y":162.27272},"Length":0.0,"Life":1,"Note":73,"Type":0},{"Position":{"X":2.0,"Y":164.65907},"Length":0.0,"Life":1,"Note":71,"Type":0},{"Position":{"X":2.0,"Y":165.68181},"Length":0.0,"Life":1,"Note":70,"Type":0},{"Position":{"X":2.0,"Y":167.04546},"Length":0.0,"Life":1,"Note":75,"Type":0},{"Position":{"X":2.0,"Y":169.77272},"Length":0.0,"Life":1,"Note":68,"Type":0},{"Position":{"X":2.0,"Y":176.59091},"Length":0.0,"Life":1,"Note":66,"Type":0}],[{"Position":{"X":3.0,"Y":0.0},"Length":0.0,"Life":1,"Note":63,"Type":0},{"Position":{"X":3.0,"Y":2.0454545},"Length":0.0,"Life":1,"Note":61,"Type":0},{"Position":{"X":3.0,"Y":6.1363635},"Length":0.0,"Life":1,"Note":56,"Type":0},{"Position":{"X":3.0,"Y":8.863636},"Length":0.0,"Life":1,"Note":56,"Type":0},{"Position":{"X":3.0,"Y":10.909091},"Length":0.0,"Life":1,"Note":78,"Type":0},{"Position":{"X":3.0,"Y":11.420454},"Length":0.0,"Life":1,"Note":76,"Type":0},{"Position":{"X":3.0,"Y":12.272727},"Length":0.0,"Life":1,"Note":78,"Type":0},{"Position":{"X":3.0,"Y":13.977272},"Length":0.0,"Life":1,"Note":71,"Type":0},{"Position":{"X":3.0,"Y":17.045454},"Length":0.0,"Life":1,"Note":68,"Type":0},{"Position":{"X":3.0,"Y":17.727272},"Length":0.0,"Life":1,"Note":68,"Type":0},{"Position":{"X":3.0,"Y":18.75},"Length":0.0,"Life":1,"Note":66,"Type":0},{"Position":{"X":3.0,"Y":19.261364},"Length":0.0,"Life":1,"Note":68,"Type":0},{"Position":{"X":3.0,"Y":20.454544},"Length":0.0,"Life":1,"Note":70,"Type":0},{"Position":{"X":3.0,"Y":24.545454},"Length":0.0,"Life":1,"Note":87,"Type":0},{"Position":{"X":3.0,"Y":26.420454},"Length":0.0,"Life":1,"Note":85,"Type":0},{"Position":{"X":3.0,"Y":28.295454},"Length":0.0,"Life":1,"Note":80,"Type":0},{"Position":{"X":3.0,"Y":31.022726},"Length":0.0,"Life":1,"Note":83,"Type":0},{"Position":{"X":3.0,"Y":31.704544},"Length":0.0,"Life":1,"Note":82,"Type":0},{"Position":{"X":3.0,"Y":33.75},"Length":0.0,"Life":1,"Note":71,"Type":0},{"Position":{"X":3.0,"Y":35.113636},"Length":0.0,"Life":1,"Note":80,"Type":0},{"Position":{"X":3.0,"Y":36.477272},"Length":0.0,"Life":1,"Note":73,"Type":0},{"Position":{"X":3.0,"Y":37.15909},"Length":0.0,"Life":1,"Note":76,"Type":0},{"Position":{"X":3.0,"Y":37.670452},"Length":0.0,"Life":1,"Note":75,"Type":0},{"Position":{"X":3.0,"Y":39.545452},"Length":0.0,"Life":1,"Note":76,"Type":0},{"Position":{"X":3.0,"Y":40.056816},"Length":0.0,"Life":1,"Note":76,"Type":0},{"Position":{"X":3.0,"Y":42.78409},"Length":0.0,"Life":1,"Note":75,"Type":0},{"Position":{"X":3.0,"Y":45.511364},"Length":0.0,"Life":1,"Note":90,"Type":0},{"Position":{"X":3.0,"Y":48.238636},"Length":0.0,"Life":1,"Note":88,"Type":0},{"Position":{"X":3.0,"Y":48.75},"Length":0.0,"Life":1,"Note":83,"Type":0},{"Position":{"X":3.0,"Y":50.454544},"Length":0.0,"Life":1,"Note":88,"Type":0},{"Position":{"X":3.0,"Y":53.011364},"Length":0.0,"Life":1,"Note":83,"Type":0},{"Position":{"X":3.0,"Y":56.590908},"Length":0.0,"Life":1,"Note":71,"Type":0},{"Position":{"X":3.0,"Y":57.10227},"Length":0.0,"Life":1,"Note":71,"Type":0},{"Position":{"X":3.0,"Y":57.613632},"Length":0.0,"Life":1,"Note":71,"Type":0},{"Position":{"X":3.0,"Y":58.806816},"Length":0.0,"Life":1,"Note":71,"Type":0},{"Position":{"X":3.0,"Y":62.045452},"Length":0.0,"Life":1,"Note":71,"Type":0},{"Position":{"X":3.0,"Y":62.556816},"Length":0.0,"Life":1,"Note":71,"Type":0},{"Position":{"X":3.0,"Y":63.06818},"Length":0.0,"Life":1,"Note":71,"Type":0},{"Position":{"X":3.0,"Y":64.090904},"Length":0.0,"Life":1,"Note":71,"Type":0},{"Position":{"X":3.0,"Y":64.60227},"Length":0.0,"Life":1,"Note":71,"Type":0},{"Position":{"X":3.0,"Y":65.454544},"Length":0.0,"Life":1,"Note":70,"Type":0},{"Position":{"X":3.0,"Y":67.329544},"Length":0.0,"Life":1,"Note":76,"Type":0},{"Position":{"X":3.0,"Y":68.01136},"Length":0.0,"Life":1,"Note":76,"Type":0},{"Position":{"X":3.0,"Y":70.90909},"Length":0.0,"Life":1,"Note":75,"Type":0},{"Position":{"X":3.0,"Y":71.420456},"Length":0.0,"Life":1,"Note":73,"Type":0},{"Position":{"X":3.0,"Y":71.931816},"Length":0.0,"Life":1,"Note":73,"Type":0},{"Position":{"X":3.0,"Y":72.954544},"Length":0.0,"Life":1,"Note":68,"Type":0},{"Position":{"X":3.0,"Y":75.0},"Length":0.0,"Life":1,"Note":68,"Type":0},{"Position":{"X":3.0,"Y":75.340904},"Length":0.0,"Life":1,"Note":68,"Type":0},{"Position":{"X":3.0,"Y":78.40909},"Length":0.0,"Life":1,"Note":90,"Type":0},{"Position":{"X":3.0,"Y":78.920456},"Length":0.0,"Life":1,"Note":88,"Type":0},{"Position":{"X":3.0,"Y":80.454544},"Length":0.0,"Life":1,"Note":87,"Type":0},{"Position":{"X":3.0,"Y":80.965904},"Length":0.0,"Life":1,"Note":85,"Type":0},{"Position":{"X":3.0,"Y":82.5},"Length":0.0,"Life":1,"Note":87,"Type":0},{"Position":{"X":3.0,"Y":84.545456},"Length":0.0,"Life":1,"Note":80,"Type":0},{"Position":{"X":3.0,"Y":85.56818},"Length":0.0,"Life":1,"Note":78,"Type":0},{"Position":{"X":3.0,"Y":86.25},"Length":0.0,"Life":1,"Note":80,"Type":0},{"Position":{"X":3.0,"Y":87.44318},"Length":0.0,"Life":1,"Note":82,"Type":0},{"Position":{"X":3.0,"Y":87.95454},"Length":0.0,"Life":1,"Note":82,"Type":0},{"Position":{"X":3.0,"Y":88.63636},"Length":0.0,"Life":1,"Note":71,"Type":0},{"Position":{"X":3.0,"Y":91.70454},"Length":0.0,"Life":1,"Note":75,"Type":0},{"Position":{"X":3.0,"Y":93.06818},"Length":0.0,"Life":1,"Note":73,"Type":0},{"Position":{"X":3.0,"Y":93.920456},"Length":0.0,"Life":1,"Note":71,"Type":0},{"Position":{"X":3.0,"Y":94.94318},"Length":0.0,"Life":1,"Note":75,"Type":0},{"Position":{"X":3.0,"Y":96.98863},"Length":0.0,"Life":1,"Note":71,"Type":0},{"Position":{"X":3.0,"Y":98.181816},"Length":0.0,"Life":1,"Note":70,"Type":0},{"Position":{"X":3.0,"Y":99.20454},"Length":0.0,"Life":1,"Note":71,"Type":0},{"Position":{"X":3.0,"Y":106.36363},"Length":0.0,"Life":1,"Note":76,"Type":0},{"Position":{"X":3.0,"Y":108.06818},"Length":0.0,"Life":1,"Note":73,"Type":0},{"Position":{"X":3.0,"Y":108.75},"Length":0.0,"Life":1,"Note":71,"Type":0},{"Position":{"X":3.0,"Y":109.431816},"Length":0.0,"Life":1,"Note":71,"Type":0},{"Position":{"X":3.0,"Y":110.11363},"Length":0.0,"Life":1,"Note":73,"Type":0},{"Position":{"X":3.0,"Y":111.81818},"Length":0.0,"Life":1,"Note":87,"Type":0},{"Position":{"X":3.0,"Y":112.32954},"Length":0.0,"Life":1,"Note":90,"Type":0},{"Position":{"X":3.0,"Y":114.20454},"Length":0.0,"Life":1,"Note":85,"Type":0},{"Position":{"X":3.0,"Y":115.56818},"Length":0.0,"Life":1,"Note":83,"Type":0},{"Position":{"X":3.0,"Y":117.44318},"Length":0.0,"Life":1,"Note":88,"Type":0},{"Position":{"X":3.0,"Y":121.02273},"Length":0.0,"Life":1,"Note":85,"Type":0},{"Position":{"X":3.0,"Y":123.57954},"Length":0.0,"Life":1,"Note":71,"Type":0},{"Position":{"X":3.0,"Y":123.920456},"Length":0.0,"Life":1,"Note":71,"Type":0},{"Position":{"X":3.0,"Y":124.431816},"Length":0.0,"Life":1,"Note":71,"Type":0},{"Position":{"X":3.0,"Y":126.13636},"Length":0.0,"Life":1,"Note":75,"Type":0},{"Position":{"X":3.0,"Y":127.5},"Length":0.0,"Life":1,"Note":70,"Type":0},{"Position":{"X":3.0,"Y":129.03409},"Length":0.0,"Life":1,"Note":71,"Type":0},{"Position":{"X":3.0,"Y":131.93181},"Length":0.0,"Life":1,"Note":71,"Type":0},{"Position":{"X":3.0,"Y":132.95454},"Length":0.0,"Life":1,"Note":95,"Type":0},{"Position":{"X":3.0,"Y":134.65909},"Length":0.0,"Life":1,"Note":75,"Type":0},{"Position":{"X":3.0,"Y":135.0},"Length":0.0,"Life":1,"Note":78,"Type":0},{"Position":{"X":3.0,"Y":139.43181},"Length":0.0,"Life":1,"Note":68,"Type":0},{"Position":{"X":3.0,"Y":143.18181},"Length":0.0,"Life":1,"Note":70,"Type":0},{"Position":{"X":3.0,"Y":143.52272},"Length":0.0,"Life":1,"Note":73,"Type":0},{"Position":{"X":3.0,"Y":143.86363},"Length":0.0,"Life":1,"Note":78,"Type":0},{"Position":{"X":3.0,"Y":145.22726},"Length":0.0,"Life":1,"Note":90,"Type":0},{"Position":{"X":3.0,"Y":146.42046},"Length":0.0,"Life":1,"Note":82,"Type":0},{"Position":{"X":3.0,"Y":146.76135},"Length":0.0,"Life":1,"Note":85,"Type":0},{"Position":{"X":3.0,"Y":147.10226},"Length":0.0,"Life":1,"Note":88,"Type":0},{"Position":{"X":3.0,"Y":147.61363},"Length":0.0,"Life":1,"Note":83,"Type":0},{"Position":{"X":3.0,"Y":149.14772},"Length":0.0,"Life":1,"Note":76,"Type":0},{"Position":{"X":3.0,"Y":150.51135},"Length":0.0,"Life":1,"Note":82,"Type":0},{"Position":{"X":3.0,"Y":151.02272},"Length":0.0,"Life":1,"Note":78,"Type":0},{"Position":{"X":3.0,"Y":151.36363},"Length":0.0,"Life":1,"Note":78,"Type":0},{"Position":{"X":3.0,"Y":152.21591},"Length":0.0,"Life":1,"Note":76,"Type":0},{"Position":{"X":3.0,"Y":152.72726},"Length":0.0,"Life":1,"Note":80,"Type":0},{"Position":{"X":3.0,"Y":153.06818},"Length":0.0,"Life":1,"Note":80,"Type":0},{"Position":{"X":3.0,"Y":154.09091},"Length":0.0,"Life":1,"Note":82,"Type":0},{"Position":{"X":3.0,"Y":155.45454},"Length":0.0,"Life":1,"Note":71,"Type":0},{"Position":{"X":3.0,"Y":158.52272},"Length":0.0,"Life":1,"Note":75,"Type":0},{"Position":{"X":3.0,"Y":161.76135},"Length":0.0,"Life":1,"Note":75,"Type":0},{"Position":{"X":3.0,"Y":163.97726},"Length":0.0,"Life":1,"Note":71,"Type":0},{"Position":{"X":3.0,"Y":165.34091},"Length":0.0,"Life":1,"Note":70,"Type":0},{"Position":{"X":3.0,"Y":166.36363},"Length":0.0,"Life":1,"Note":71,"Type":0},{"Position":{"X":3.0,"Y":171.13635},"Length":0.0,"Life":1,"Note":66,"Type":0},{"Position":{"X":3.0,"Y":172.5},"Length":0.0,"Life":1,"Note":64,"Type":0}]],"Difficulty":1,"Song":"Memories"}